LICENSE.txt
README.md
setup.cfg
setup.py
CSVToListDict/CSVToListDict.py
CSVToListDict/__init__.py
CSVToListDict.egg-info/PKG-INFO
CSVToListDict.egg-info/SOURCES.txt
CSVToListDict.egg-info/dependency_links.txt
CSVToListDict.egg-info/top_level.txt