Metadata-Version: 2.1
Name: CSVToListDict
Version: 0.1
Summary: Takes any input csv, and returns a List[dict] of its contents.
Home-page: https://github.com/amcsparron2793-Water/CSVToListDict
Download-URL: https://github.com/amcsparron2793-Water/CSVToListDict/archive/refs/tags/0.1.tar.gz
Author: Amcsparron
Author-email: amcsparron@albanyny.gov
License: MIT License
Keywords: csv,converter
License-File: LICENSE.txt
